{
    "tagname": "div",
    "lnk1": {
        "tagname": "lnk",
        "ajax": "https:\/\/github.com\/wise-penny\/pipes",
        "textContent": "GitHub + ",
        "class": "redirect",
        "id": "necessary"
    },
    "lnk2": {
        "tagname": "lnk",
        "ajax": "https:\/\/paypal.me\/pirodock",
        "textContent": "Donate",
        "class": "redirect",
        "id": "ids-required"
    },
    "car54": {
        "id": "stuffer-left",
        "tagname": "input",
        "class": "decrIndex carousel-ajax",
        "onclick": "carousel('carousel0')",
        "type": "button",
        "value": "up"
    },
    "car2n": {
        "id": "stuffer-right",
        "tagname": "input",
        "onclick": "carousel('carousel0')",
        "type": "button",
        "value": "down",
        "file-index": "0"
    },
    "br1": {
        "tagname": "br"
    },
    "car11": {
        "tagname": "carousel",
        "style": "height:200;width:400;",
        "file-index": "0",
        "boxes": "7",
        "class": "carousel-auto-off carousel-ajax",
        "height": "200",
        "width": "200",
	"interval": "2",
        "file-order": "modala.json;modala.json;modala2.json",
        "insert": "carousel0",
        "id": "carousel0"
    },
    "br2": {
        "tagname": "br"
    },
    "card": {
        "tagname": "carousel",
        "style": "height:200;width:400;",
        "file-index": "0",
        "boxes": "10",
        "delay": "5000",
        "height": "200",
        "width": "200",
	"interval": "3",
        "class": "carousel-vert decrIndex",
        "file-order": "grid.png;grid2.png;grid3.png;grid2.png;grid4.png;grid2.png;grid3.png",
        "insert": "carousel2",
        "id": "carousel2"
    },
    "gk": {
        "tagname": "timed",
        "class": "set-attr",
        "set-attr": "value",
        "delay": "3000",
        "ajax": "button_src.php",
        "insert": "gutty-button",
        "id": "timer1"
    },
    "h": {
        "tagname": "div",
        "style": "height:150;width:200;background-color:#abcdef;",
        "textContent": "technically *I* was floating",
        "class": "oiwfiriro",
        "guts": {
            "tagname": "p",
            "innerText": "eowfwuioe",
            "style": "justify-content:center;color:#ffffff;width:96%;border:#ffffff solid;",
            "gutty": {
                "tagname": "input",
                "id": "gutty-button",
                "type": "button",
                "value": "eowfwuioe",
                "style": "justify-content:center;"
            }
        },
        "guts1": {
            "tagname": "p",
            "innerText": "eowfwuioe",
            "style": "justify-content:center;color:#ffffff;width:96%;border:#ffffff solid;",
            "gutty": {
                "tagname": "input",
                "type": "button",
                "value": "eowfwuioe",
                "style": "justify-content:center;"
            }
        }
    },
    "g": {
        "tagname": "div",
        "style": "height:150;width:200;background-color:#abcdef;",
        "textContent": "technically *I* was floating",
        "guts": {
            "tagname": "p",
            "innerText": "eowfwuioe",
            "style": "justify-content:center;color:#ffffff;width:96%;border:#ffffff solid;",
            "gutty": {
                "tagname": "input",
                "type": "button",
                "value": "eowfwuioe",
                "style": "justify-content:center;"
            }
        }
    },
    "mo": {
        "tagname": "span",
        "display": "mo-id",
        "class": "mouse-over",
        "textContent": "It was somewhere over here",
        "id": "mo-init",
        "guts": {
            "tagname": "dyn",
            "innerText": "Donate",
            "class": "redirect",
            "ajax": "https://www.paypal.me/pirodock",
            "style": "display:none",
            "id": "mo-id"
        }
    }
}
